aelcha/__init__.py
aelcha/common.py
aelcha/core.py
aelcha/draft.md
aelcha/process_maccor_data_legacy.py
aelcha/user_interface.py
aelcha/data_model/__init__.py
aelcha/data_model/class_diagram.md
aelcha/data_model/core.py
aelcha/data_model/electrochemistry.py
aelcha/data_model/items.py
aelcha/data_model/qaq_data.py
aelcha/data_model/quantities.py
aelcha/data_model/units_of_measure.py
aelcha-0.7.0.dist-info/LICENSE.txt
aelcha-0.7.0.dist-info/METADATA
aelcha-0.7.0.dist-info/WHEEL
aelcha-0.7.0.dist-info/top_level.txt
aelcha-0.7.0.dist-info/RECORD
