Metadata-Version: 2.2
Name: aelcha
Version: 0.7.0
Summary: A Python package providing the code for Automated Electrochemical Analysis (aElChA)
Home-page: https://github.com/LukasGold/aelcha-package/
Author: Lukas Gold
Author-email: lukas.gold@isc.fraunhofer.de
License: AGPL-3.0-or-later
Project-URL: Documentation, https://github.com/LukasGold/aelcha-package/README.md
Platform: any
Classifier: Development Status :: 3 - Alpha
Classifier: Programming Language :: Python
Requires-Python: >=3.8
License-File: LICENSE.txt
Requires-Dist: batt-utility
Requires-Dist: bs4
Requires-Dist: digatron-utility
Requires-Dist: maccor-utility
Requires-Dist: matplotlib
Requires-Dist: numpy
Requires-Dist: openpyxl
Requires-Dist: pandas
Requires-Dist: pydantic
Requires-Dist: sphinx
Requires-Dist: scipy
Requires-Dist: typing_extensions
Requires-Dist: uncertainties
Provides-Extra: testing
Requires-Dist: setuptools; extra == "testing"
Requires-Dist: pytest; extra == "testing"
Requires-Dist: pytest-cov; extra == "testing"
Provides-Extra: dev
Requires-Dist: pre-commit; extra == "dev"
Requires-Dist: tox; extra == "dev"
Provides-Extra: all
Requires-Dist: setuptools; extra == "all"
Requires-Dist: pytest; extra == "all"
Requires-Dist: pytest-cov; extra == "all"
Requires-Dist: pre-commit; extra == "all"
Requires-Dist: tox; extra == "all"
